LICENSE
MANIFEST.in
README.md
logo.png
setup.py
captcha_harvester.egg-info/PKG-INFO
captcha_harvester.egg-info/SOURCES.txt
captcha_harvester.egg-info/dependency_links.txt
captcha_harvester.egg-info/entry_points.txt
captcha_harvester.egg-info/top_level.txt
harvester/__init__.py
harvester/browser.py
harvester/entry_point.py
harvester/fetch.py
harvester/server/__init__.py
harvester/server/expiring_queue.py
harvester/server/icon.png
harvester/server/style.css
harvester/server/templates/domains.html
harvester/server/templates/ga.chunk.html
harvester/server/templates/hcaptcha.html
harvester/server/templates/recaptcha-v2.html
harvester/server/templates/recaptcha-v3.html